ingestclient/__init__.py
ingestclient/client.py
ingestclient/prep_ingest.py
ingestclient/configs/boss-v0.1-catmaid-file-stack-example.json
ingestclient/configs/boss-v0.1-catmaid-url-stack-example.json
ingestclient/configs/boss-v0.1-hdf5Chunk-example.json
ingestclient/configs/boss-v0.1-hdf5SingleFile-example.json
ingestclient/configs/boss-v0.1-hdf5TimeSeries-example.json
ingestclient/configs/boss-v0.1-intern-example.json
ingestclient/configs/boss-v0.1-tiff-hyperstack-example.json
ingestclient/configs/boss-v0.1-time-series-example.json
ingestclient/configs/boss-v0.1-zStack-example.json
ingestclient/configs/boss-v0.2-cloudvolume-example.json
ingestclient/core/__init__.py
ingestclient/core/backend.py
ingestclient/core/config.py
ingestclient/core/consts.py
ingestclient/core/engine.py
ingestclient/core/validator.py
ingestclient/plugins/__init__.py
ingestclient/plugins/catmaid.py
ingestclient/plugins/chunk.py
ingestclient/plugins/cloudvolume.py
ingestclient/plugins/hdf5.py
ingestclient/plugins/intern.py
ingestclient/plugins/multipage_tiff.py
ingestclient/plugins/path.py
ingestclient/plugins/stack.py
ingestclient/plugins/tile.py
ingestclient/plugins/zarr.py
ingestclient/schema/boss-v0.1-schema.json
ingestclient/schema/boss-v0.2-schema.json
ingestclient/utils/__init__.py
ingestclient/utils/backoff.py
ingestclient/utils/console.py
ingestclient/utils/filesystem.py
ingestclient/utils/log.py
ingestclient/utils/queue.py
boss_ingest-0.12.0.dist-info/LICENSE
boss_ingest-0.12.0.dist-info/METADATA
boss_ingest-0.12.0.dist-info/WHEEL
boss_ingest-0.12.0.dist-info/entry_points.txt
boss_ingest-0.12.0.dist-info/top_level.txt
boss_ingest-0.12.0.dist-info/RECORD
