Metadata-Version: 2.1
Name: boss-ingest
Version: 0.12.0
Summary: Ingest client for the Boss
Home-page: https://github.com/jhuapl-boss/ingest-client
Author: Johns Hopkins University Applied Physics Laboratory
Author-email: iarpamicrons@jhuapl.edu
License: Apache 2.0
Keywords: brain,microscopy,neuroscience,connectome,connectomics,spatial,EM,electron,calcium,database,boss,microns,iarpa,jhu
Platform: UNKNOWN
Classifier: Development Status :: 4 - Beta
Classifier: Programming Language :: Python :: 3.8
Classifier: Programming Language :: Python :: 3.7
Classifier: Programming Language :: Python :: 3.6
Requires-Dist: mock (>=4.0.3)
Requires-Dist: jsonschema (>=2.5.1)
Requires-Dist: requests (>=2.25.1)
Requires-Dist: responses (>=0.12.1)
Requires-Dist: urllib3 (>=1.25.10)
Requires-Dist: boto3 (>=1.16.54)
Requires-Dist: moto (<2.0.0,>=1.3.16)
Requires-Dist: Pillow (>=3.3.1)
Requires-Dist: numpy (>=1.11.1)
Requires-Dist: intern (>=1.2.0)
Requires-Dist: six (>=1.15.0)
